Metadata-Version: 1.1
Name: asre-compute
Version: 0.0.12
Summary: New class release of the ASRE package.
Home-page: UNKNOWN
Author: François Grolleau
Author-email: francois.grolleau@aphp.fr
License: MIT
Platform: UNKNOWN
Classifier: Development Status :: 5 - Production/Stable
Classifier: Intended Audience :: Education
Classifier: Operating System :: Microsoft :: Windows :: Windows 10
Classifier: License :: OSI Approved :: MIT License
Classifier: Programming Language :: Python :: 3
